{"sections":{"image_banner":{"type":"image-banner","blocks":{"text":{"type":"text","settings":{"text":"CARRY YOUR ESSENTIALS WITH CLASS","text_style":"caption-with-letter-spacing"}},"heading":{"type":"heading","settings":{"heading":"Function Meets Fashion","heading_size":"h1"}},"button":{"type":"buttons","settings":{"button_label_1":"Shop all","button_link_1":"shopify:\/\/collections\/all","button_style_secondary_1":false,"button_label_2":"","button_link_2":"","button_style_secondary_2":false}}},"block_order":["text","heading","button"],"settings":{"image":"shopify:\/\/shop_images\/Hero.jpg","image_overlay_opacity":50,"image_height":"small","desktop_content_position":"middle-left","show_text_box":false,"desktop_content_alignment":"left","color_scheme":"scheme-5","image_behavior":"none","mobile_content_alignment":"center","stack_images_on_mobile":true,"show_text_below":false}},"multicolumn":{"type":"multicolumn","blocks":{"column4":{"type":"column","settings":{"title":"Insert partner logo","text":"","link_label":"","link":""}},"column5":{"type":"column","settings":{"title":"Insert partner logo","text":"","link_label":"","link":""}},"column6":{"type":"column","settings":{"title":"Insert partner logo","text":"","link_label":"","link":""}}},"block_order":["column4","column5","column6"],"disabled":true,"settings":{"title":"","heading_size":"h1","image_width":"full","image_ratio":"adapt","columns_desktop":6,"column_alignment":"center","background_style":"none","button_label":"","button_link":"","color_scheme":"scheme-2","columns_mobile":"2","swipe_on_mobile":true,"padding_top":12,"padding_bottom":12}},"rich_text":{"type":"rich-text","blocks":{"text":{"type":"text","settings":{"text":"<p>QUALITY | SUSTAINABILITY | INDIVIDUALITY<\/p>"}}},"block_order":["text"],"settings":{"desktop_content_position":"center","content_alignment":"center","color_scheme":"scheme-3","full_width":true,"padding_top":4,"padding_bottom":4}},"featured_collection1":{"type":"featured-collection","settings":{"title":"New Arrivals","heading_size":"h2","description":"","show_description":false,"description_style":"body","collection":"new-arrivals","products_to_show":5,"columns_desktop":5,"full_width":false,"show_view_all":true,"view_all_style":"outline","enable_desktop_slider":false,"color_scheme":"","image_ratio":"adapt","image_shape":"default","show_secondary_image":false,"show_vendor":false,"show_rating":false,"quick_add":"none","columns_mobile":"2","swipe_on_mobile":false,"padding_top":36,"padding_bottom":52}},"collection_list":{"type":"collection-list","blocks":{"featured_collection1":{"type":"featured_collection","settings":{"collection":"backpacks"}},"featured_collection2":{"type":"featured_collection","settings":{"collection":"duffles"}},"featured_collection_VdFnhT":{"type":"featured_collection","settings":{"collection":"small-bags"}},"featured_collection3":{"type":"featured_collection","settings":{"collection":"coolers"}},"featured_collection_cRWWHX":{"type":"featured_collection","settings":{"collection":"kits"}}},"block_order":["featured_collection1","featured_collection2","featured_collection_VdFnhT","featured_collection3","featured_collection_cRWWHX"],"settings":{"title":"Our Top Categories","heading_size":"h2","image_ratio":"square","columns_desktop":5,"color_scheme":"scheme-4","show_view_all":true,"columns_mobile":"2","swipe_on_mobile":false,"padding_top":48,"padding_bottom":60}},"slideshow_LLNx8t":{"type":"slideshow","blocks":{"slide_3F8jBU":{"type":"slide","settings":{"image":"shopify:\/\/shop_images\/slide_1.webp","heading":"","heading_size":"h1","subheading":"","button_label":"","link":"","button_style_secondary":false,"box_align":"middle-center","show_text_box":false,"text_alignment":"center","image_overlay_opacity":0,"color_scheme":"","text_alignment_mobile":"center"}},"slide_iKGxjd":{"type":"slide","settings":{"image":"shopify:\/\/shop_images\/slide_2.jpg","heading":"","heading_size":"h1","subheading":"","button_label":"","link":"","button_style_secondary":false,"box_align":"middle-center","show_text_box":false,"text_alignment":"center","image_overlay_opacity":0,"color_scheme":"","text_alignment_mobile":"center"}},"slide_kkJpkc":{"type":"slide","settings":{"image":"shopify:\/\/shop_images\/slide_3.jpg","heading":"","heading_size":"h1","subheading":"","button_label":"","link":"","button_style_secondary":false,"box_align":"middle-center","show_text_box":false,"text_alignment":"center","image_overlay_opacity":0,"color_scheme":"","text_alignment_mobile":"center"}}},"block_order":["slide_3F8jBU","slide_iKGxjd","slide_kkJpkc"],"settings":{"layout":"full_bleed","slide_height":"medium","slider_visual":"counter","auto_rotate":false,"change_slides_speed":5,"image_behavior":"none","show_text_below":true,"accessibility_info":"Slideshow about our brand"}},"featured_product_6Y8wzU":{"type":"featured-product","blocks":{"text_qVEBT7":{"type":"text","settings":{"text":"{{ section.settings.product.vendor }}","text_style":"uppercase"}},"title_BYkkRM":{"type":"title","settings":{"heading_size":"h1"}},"price_KJjfxF":{"type":"price","settings":{}},"variant_picker_dcYLPx":{"type":"variant_picker","settings":{"picker_type":"button","swatch_shape":"circle"}},"quantity_selector_Pfj6iC":{"type":"quantity_selector","settings":{}},"buy_buttons_BryrxC":{"type":"buy_buttons","settings":{"show_dynamic_checkout":true,"show_gift_card_recipient":true}},"share_ipxhXJ":{"type":"share","settings":{"share_label":"Share"}}},"block_order":["text_qVEBT7","title_BYkkRM","price_KJjfxF","variant_picker_dcYLPx","quantity_selector_Pfj6iC","buy_buttons_BryrxC","share_ipxhXJ"],"settings":{"product":"rolltop-limited","color_scheme":"","secondary_background":false,"media_size":"medium","constrain_to_viewport":true,"media_fit":"contain","media_position":"left","image_zoom":"lightbox","hide_variants":false,"enable_video_looping":false,"padding_top":36,"padding_bottom":36}},"collage_bkhc8e":{"type":"collage","blocks":{"image_89MAJh":{"type":"image","settings":{"image":"shopify:\/\/shop_images\/Gallery.webp"}},"product_QQnJNX":{"type":"product","settings":{"product":"small-bag","second_image":false}},"collection_Mw8J9d":{"type":"collection","settings":{"collection":"small-bags"}}},"block_order":["image_89MAJh","product_QQnJNX","collection_Mw8J9d"],"settings":{"heading":"Multimedia collage","heading_size":"h1","desktop_layout":"left","mobile_layout":"column","card_styles":"product-card-wrapper","color_scheme":"","padding_top":36,"padding_bottom":36}}},"order":["image_banner","multicolumn","rich_text","featured_collection1","collection_list","slideshow_LLNx8t","featured_product_6Y8wzU","collage_bkhc8e"]}